markdown_hide_code/__init__.py
markdown_hide_code/main.py
markdown_hide_code-0.1.1.dist-info/licenses/LICENSE
markdown_hide_code-0.1.1.dist-info/METADATA
markdown_hide_code-0.1.1.dist-info/WHEEL
markdown_hide_code-0.1.1.dist-info/top_level.txt
markdown_hide_code-0.1.1.dist-info/RECORD
