Metadata-Version: 2.4
Name: markdown-hide-code
Version: 0.1.1
Summary: Hide code blocks from the rendered markdown output, useful for running tests on your documentation.
Author-email: Martin Staadecker <machstg@gmail.com>
License-Expression: MIT
Project-URL: repository, https://github.com/staadecker/markdown-hide-code/
Project-URL: Issues, https://github.com/staadecker/markdown-hide-code/issues
Classifier: Programming Language :: Python :: 3
Classifier: Operating System :: OS Independent
Classifier: Development Status :: 3 - Alpha
Classifier: Natural Language :: English
Requires-Python: >=3.9
License-File: LICENSE
Requires-Dist: Markdown
Requires-Dist: pymdown-extensions>=8.0
Dynamic: license-file
